Metadata-Version: 2.1
Name: odoo8-addon-account-payment-return-import
Version: 8.0.1.0.0.99.dev27
Summary: This module add a generic wizard to import payment return fileformats. Is only the base to be extended by another modules
Home-page: https://www.tecnativa.com
Author: Tecnativa,Odoo Community Association (OCA)
Author-email: support@odoo-community.org
License: AGPL-3
Platform: UNKNOWN
Classifier: Programming Language :: Python
Classifier: Framework :: Odoo
Classifier: Framework :: Odoo :: 8.0
Classifier: License :: OSI Approved :: GNU Affero General Public License v3
Requires-Python: ~=2.7
Requires-Dist: odoo8-addon-account-payment-return
Requires-Dist: odoo (<9.0a,>=8.0a)
